synapkit/__init__.py
synapkit/_version.py
synapkit/agent.py
synapkit-0.0.2.dist-info/METADATA
synapkit-0.0.2.dist-info/WHEEL
synapkit-0.0.2.dist-info/licenses/LICENSE
synapkit-0.0.2.dist-info/RECORD
